lcoptview/__init__.py
lcoptview/app.cfg
lcoptview/excel_functions.py
lcoptview/flask_gui.py
lcoptview/modelview.py
lcoptview/parameters.py
lcoptview/bin/launch_lcoptview.py
lcoptview/static/css/lv_analysis.css
lcoptview/static/css/lv_parameter_table.css
lcoptview/static/css/lv_sandbox.css
lcoptview/static/css/lv_style.css
lcoptview/static/css/lv_treetest.css
lcoptview/static/css/cdn_cache/Muli-Regular.ttf
lcoptview/static/css/cdn_cache/bootstrap-dialog.min.css
lcoptview/static/css/cdn_cache/bootstrap-select.min.css
lcoptview/static/css/cdn_cache/bootstrap.min.css
lcoptview/static/css/cdn_cache/font-awesome.min.css
lcoptview/static/css/cdn_cache/jquery-ui.css
lcoptview/static/css/cdn_cache/material-icons.css
lcoptview/static/css/cdn_cache/material-icons.woff2
lcoptview/static/css/cdn_cache/selectize.css
lcoptview/static/css/cdn_cache/images/ui-bg_flat_75_ffffff_40x100.png
lcoptview/static/css/cdn_cache/images/ui-icons_222222_256x240.png
lcoptview/static/css/cdn_cache/images/ui-icons_555555_256x240.png
lcoptview/static/css/cdn_cache/images/ui-icons_777620_256x240.png
lcoptview/static/css/cdn_cache/images/ui-icons_777777_256x240.png
lcoptview/static/css/cdn_cache/images/ui-icons_cc0000_256x240.png
lcoptview/static/css/cdn_cache/images/ui-icons_ffffff_256x240.png
lcoptview/static/js/analysis.js
lcoptview/static/js/comparison_bar.js
lcoptview/static/js/export_chart.js
lcoptview/static/js/hotspot.js
lcoptview/static/js/lv_sandbox.js
lcoptview/static/js/lv_sandbox_functions.js
lcoptview/static/js/md5.js
lcoptview/static/js/new_stacked_bar.js
lcoptview/static/js/pie2.js
lcoptview/static/js/result_table.js
lcoptview/static/js/stacked_bar.js
lcoptview/static/js/table-edit.js
lcoptview/static/js/treetest2.js
lcoptview/static/js/cdn_cache/bootstrap-dialog.min.js
lcoptview/static/js/cdn_cache/bootstrap-select.js
lcoptview/static/js/cdn_cache/bootstrap.min.js
lcoptview/static/js/cdn_cache/d3-legend.js
lcoptview-0.1.4.dist-info/DESCRIPTION.rst
lcoptview-0.1.4.dist-info/METADATA
lcoptview-0.1.4.dist-info/RECORD
lcoptview-0.1.4.dist-info/WHEEL
lcoptview-0.1.4.dist-info/entry_points.txt
lcoptview-0.1.4.dist-info/metadata.json
lcoptview-0.1.4.dist-info/top_level.txt
