Metadata-Version: 2.0
Name: lcoptview
Version: 0.1.4
Summary: UNKNOWN
Home-page: https://github.com/pjamesjoyce/lcoptview/
Author: P. James Joyce
Author-email: pjamesjoyce@gmail.com
License: Copyright 2017 P. James Joyce
Requires-Dist: Flask (>=0.7.2)
Requires-Dist: xlsxwriter
